mesmer/__init__.py
mesmer/testing.py
mesmer/calibrate_mesmer/__init__.py
mesmer/calibrate_mesmer/calibrate_mesmer.py
mesmer/calibrate_mesmer/train_gt.py
mesmer/calibrate_mesmer/train_gv.py
mesmer/calibrate_mesmer/train_lt.py
mesmer/calibrate_mesmer/train_lv.py
mesmer/calibrate_mesmer/train_utils.py
mesmer/core/__init__.py
mesmer/core/_data.py
mesmer/core/geospatial.py
mesmer/core/grid.py
mesmer/core/mask.py
mesmer/core/regionmaskcompat.py
mesmer/core/utils.py
mesmer/core/volc.py
mesmer/core/weighted.py
mesmer/create_emulations/__init__.py
mesmer/create_emulations/create_emus_gt.py
mesmer/create_emulations/create_emus_gv.py
mesmer/create_emulations/create_emus_lt.py
mesmer/create_emulations/create_emus_lv.py
mesmer/create_emulations/make_realisations.py
mesmer/create_emulations/merge_emus.py
mesmer/create_emulations/utils.py
mesmer/io/__init__.py
mesmer/io/_load_cmipng.py
mesmer/io/load_constant_files.py
mesmer/io/load_mesmer.py
mesmer/io/load_obs.py
mesmer/io/save_mesmer_bundle.py
mesmer/stats/__init__.py
mesmer/stats/_auto_regression.py
mesmer/stats/_gaspari_cohn.py
mesmer/stats/_linear_regression.py
mesmer/stats/_localized_covariance.py
mesmer/stats/_smoothing.py
mesmer/utils/__init__.py
mesmer/utils/convert.py
mesmer/utils/select.py
mesmer_emulator-0.10.0.dist-info/AUTHORS
mesmer_emulator-0.10.0.dist-info/LICENSE
mesmer_emulator-0.10.0.dist-info/METADATA
mesmer_emulator-0.10.0.dist-info/WHEEL
mesmer_emulator-0.10.0.dist-info/top_level.txt
mesmer_emulator-0.10.0.dist-info/RECORD
