Metadata-Version: 2.1
Name: mesmer-emulator
Version: 0.10.0
Summary: Modular Earth System Model Emulator with spatially Resolved output
Home-page: https://github.com/MESMER-group/mesmer
Author: mesmer developers
Author-email: mesmer@env.ethz.ch
License: GPLv3+
Project-URL: Documentation, https://mesmer-emulator.readthedocs.io
Project-URL: Source, https://github.com/MESMER-group/mesmer
Project-URL: BugReports, https://github.com/MESMER-group/mesmer/issues
Keywords: climate atmosphere "Earth System Model Emulator"
Classifier: Development Status :: 4 - Beta
Classifier: License :: OSI Approved :: GNU General Public License v3 or later (GPLv3+)
Classifier: Operating System :: OS Independent
Classifier: Intended Audience :: Science/Research
Classifier: Programming Language :: Python
Classifier: Programming Language :: Python :: 3
Classifier: Programming Language :: Python :: 3.9
Classifier: Programming Language :: Python :: 3.10
Classifier: Programming Language :: Python :: 3.11
Classifier: Programming Language :: Python :: 3.12
Classifier: Topic :: Scientific/Engineering
Classifier: Topic :: Scientific/Engineering :: Atmospheric Science
Requires-Python: >=3.9
License-File: LICENSE
License-File: AUTHORS
Requires-Dist: dask[complete]
Requires-Dist: numpy
Requires-Dist: packaging
Requires-Dist: pandas >=2.0
Requires-Dist: pooch
Requires-Dist: regionmask
Requires-Dist: scikit-learn
Requires-Dist: statsmodels
Requires-Dist: xarray >=2023.04
Provides-Extra: dev
Requires-Dist: numpydoc ; extra == 'dev'
Requires-Dist: sphinx-book-theme ; extra == 'dev'
Requires-Dist: sphinx ; extra == 'dev'
Requires-Dist: pytest-cov ; extra == 'dev'
Requires-Dist: pytest-xdist ; extra == 'dev'
Requires-Dist: pytest ; extra == 'dev'
Requires-Dist: black <23 ; extra == 'dev'
Requires-Dist: flake8 ; extra == 'dev'
Requires-Dist: isort ; extra == 'dev'
Requires-Dist: twine ; extra == 'dev'
Provides-Extra: docs
Requires-Dist: numpydoc ; extra == 'docs'
Requires-Dist: sphinx-book-theme ; extra == 'docs'
Requires-Dist: sphinx ; extra == 'docs'
Provides-Extra: tests
Requires-Dist: pytest-cov ; extra == 'tests'
Requires-Dist: pytest-xdist ; extra == 'tests'
Requires-Dist: pytest ; extra == 'tests'
